{
  "updatedAt": "2026-07-22T19:46:36.038Z",
  "source": "https://www.youtube.com/feeds/videos.xml?channel_id=UC44B4Jzwvz4pbuZW9tuSjAg",
  "channelId": "UC44B4Jzwvz4pbuZW9tuSjAg",
  "videos": [
    {
      "id": "bvRN0YrlqHY",
      "title": "利未記敬拜之歌 Leviticus Worship｜使我成為聖潔 Make Me Holy｜聖經66卷敬拜計畫 03",
      "description": "《使我成為聖潔》是「聖經66卷敬拜計畫」第 03 首，以《利未記》為根基創作的原創敬拜詩歌。 《利未記》記載了會幕、祭壇、祭司、贖罪日與禧年，也向我們顯明：聖潔的神渴望住在祂的百姓中間，並親自為人預備一條親近祂的道路。...",
      "label": "Latest Release",
      "publishedAt": "2026-07-22T18:30:36+00:00"
    },
    {
      "id": "LZYGa7KN_r0",
      "title": "祂好愛我｜無論高山低谷，祂從未放手",
      "description": "中文歌名：祂好愛我 English title: He Loves Me So Much 原視頻： 一首關於基督無條件之愛與全然交託的華語原創敬拜詩歌。無論走過高山或低谷，在軟弱與迷失之中，祂仍以不改變的愛牽引我們，從未放手。...",
      "label": "Latest Release",
      "publishedAt": "2026-07-22T07:27:26+00:00"
    },
    {
      "id": "tDv8VegSehs",
      "title": "祢領我出黑暗｜祢的應許必帶我前行",
      "description": "中文歌名：祢領我出黑暗 English title: You Led Me Out of Darkness 原視頻：...",
      "label": "Latest Release",
      "publishedAt": "2026-07-20T19:20:54+00:00"
    },
    {
      "id": "4g4Tj2OTmac",
      "title": "祂好愛我 He Loves Me So Much｜在十架上毫無保留的愛｜原創敬拜詩歌 | 當你感到軟弱，記得祂從未放手",
      "description": "《祂好愛我》是一首關於基督無條件之愛與全然交託的原創敬拜詩歌。 當我們軟弱、迷失，甚至懷疑自己走錯道路時，祂仍以慈繩愛索牽引我們，用釘痕的雙手溫柔扶住我們。祂的愛不是因為我們做對了什麼，而是在我們還軟弱時，祂已經為我們毫無保留地付上生命。...",
      "label": "Latest Release",
      "publishedAt": "2026-07-19T12:21:06+00:00"
    },
    {
      "id": "iLcpUBxl8qw",
      "title": "祢領我出黑暗｜祢為我開道路",
      "description": "中文歌名：祢領我出黑暗 English title: You Led Me Out of Darkness 原視頻：...",
      "label": "Latest Release",
      "publishedAt": "2026-07-18T05:56:59+00:00"
    },
    {
      "id": "LIhP7DzO2lc",
      "title": "願祢復興這地｜願復興先從我開始",
      "description": "中文歌名：願祢復興這地 English title: Revive This Land, O Lord 原視頻： 一首從個人悔改開始，為教會、家庭、城市與萬民復興呼求的原創華語敬拜詩歌。願聖靈重新點燃祭壇的火，使復興先從我的心開始。...",
      "label": "Latest Release",
      "publishedAt": "2026-07-16T19:33:35+00:00"
    }
  ]
}
